nigeriabulksms_sdk/__init__.py
nigeriabulksms_sdk/client.py
nigeriabulksms_sdk/exceptions.py
nigeriabulksms_sdk/services/__init__.py
nigeriabulksms_sdk/services/audio.py
nigeriabulksms_sdk/services/call.py
nigeriabulksms_sdk/services/data.py
nigeriabulksms_sdk/services/sms.py
nigeriabulksms_sdk-1.0.0.dist-info/licenses/LICENSE
tests/__init__.py
tests/test_client.py
tests/test_sms.py
nigeriabulksms_sdk-1.0.0.dist-info/METADATA
nigeriabulksms_sdk-1.0.0.dist-info/WHEEL
nigeriabulksms_sdk-1.0.0.dist-info/top_level.txt
nigeriabulksms_sdk-1.0.0.dist-info/RECORD
