Metadata-Version: 2.4
Name: nigeriabulksms-sdk
Version: 1.0.0
Summary: A Python SDK for the NigeriaBulkSMS API.
Home-page: https://github.com/timothydake/nigeriabulksms-python-sdk
Author: Timothy Dake
Author-email: timdake4@gmail.com
Project-URL: Bug Tracker, https://github.com/timothydake/nigeriabulksms-python-sdk/issues
Project-URL: Documentation, https://github.com/timothydake/nigeriabulksms-python-sdk#readme
Project-URL: Source Code, https://github.com/timothydake/nigeriabulksms-python-sdk
Keywords: sms,bulk sms,nigeria,messaging,api,sdk,voice,tts
Classifier: Development Status :: 5 - Production/Stable
Classifier: Intended Audience :: Developers
Classifier: Topic :: Communications :: Telephony
Classifier: Topic :: Software Development :: Libraries :: Python Modules
Classifier: Programming Language :: Python :: 3
Classifier: Programming Language :: Python :: 3.6
Classifier: Programming Language :: Python :: 3.7
Classifier: Programming Language :: Python :: 3.8
Classifier: Programming Language :: Python :: 3.9
Classifier: Programming Language :: Python :: 3.10
Classifier: Programming Language :: Python :: 3.11
Classifier: Programming Language :: Python :: 3.12
Classifier: License :: OSI Approved :: MIT License
Classifier: Operating System :: OS Independent
Requires-Python: >=3.6
License-File: LICENSE
Requires-Dist: requests>=2.25.1
Dynamic: author
Dynamic: author-email
Dynamic: classifier
Dynamic: description
Dynamic: description-content-type
Dynamic: home-page
Dynamic: keywords
Dynamic: license-file
Dynamic: project-url
Dynamic: requires-dist
Dynamic: requires-python
Dynamic: summary
